[{
    "id": 1,
    "name": "Robert Lewandowski",
    "present-club": "Bayern Munich",
    "country": "Poland",
    "salary": 451,
    "image": "https://media.guim.co.uk/b16aaf102c89fa6ce96f79086e9048be3c9eb3f5/0_71_1513_908/500.jpg"
  }, {
    "id": 2,
    "name": "Lionel Messi",
    "present-club": "Barcelona",
    "country": "Argentina",
    "salary": 838,
    "image": "https://media.guim.co.uk/f8ba3e13caceff1db8e8d619b31b5740b32a9d56/0_211_3668_2201/500.jpg"
  }, {
    "id": 3,
    "name": "Cristiano Ronaldo",
    "present-club":"Juventus",
    "country": "Portugal",
    "salary": 551,
    "image": "https://media.guim.co.uk/7c08567cb882324c62fbe21efb9f597901c09015/0_146_3500_2101/500.jpg"
  }, {
    "id": 4,
    "name": "Mohamed Salah",
    "present-club": "Egypt",
    "country": "Kali Mc Dermid",
    "salary": 444,
    "image": "https://media.guim.co.uk/faa2b736ade0e84aa023893728cd7cd52a3a465b/0_122_3600_2159/500.jpg"
  }, {
    "id": 5,
    "name": "Kevin De Bruyne",
    "present-club": "Ursa Pennacci",
    "country": "Konstantine Suffield",
    "salary": 178,
    "image": "https://media.guim.co.uk/ab50ac60df2610b75515a70fc22cc7a7cffda944/0_88_3794_2276/500.jpg"
  }, {
    "id": 6,
    "name": "Neymar",
    "present-club": "PSG",
    "country": "Brazil",
    "salary": 290,
    "image": "https://media.guim.co.uk/7824f30b00c0762007eb6d508824ca0b8c023b61/0_304_4559_2736/500.jpg"
  }, {
    "id": 7,
    "name": "Sadio Mané",
    "present-club": "Salomone Wickrath",
    "country": "Senegal",
    "salary": 536,
    "image": "https://media.guim.co.uk/59afff7ca9be00f5bfb56f65b4dd526d0d4d334b/0_269_5182_3110/500.jpg"
  }, {
    "id": 8,
    "name": "Erling Braut Haaland",
    "present-club": "Tony Mingardi",
    "country": "Norway",
    "salary": 187,
    "image": "https://media.guim.co.uk/96ed4d1b724642796cf86ddc82a89238a03bd3e1/0_60_3708_2225/500.jpg"
  }, {
    "id": 9,
    "name": "Kylian Mbappé",
    "present-club": "Elayne Goddman",
    "country": "France",
    "salary": 520,
    "image": "https://media.guim.co.uk/eb77264a8e3d9359bc4566720f2c3ad325d7a371/0_234_4961_2976/500.jpg"
  }, {
    "id": 10,
    "name": "Virgil van Dijk",
    "present-club": "Sibyl Boycott",
    "country": "Netherlands",
    "salary": 577,
    "image": "https://media.guim.co.uk/719528873f80acc6491b2ec9284c4fe4eddce901/126_323_2713_1629/500.jpg"
  }, {
    "id": 11,
    "name": "Joshua Kimmich",
    "present-club": "Renate Borchardt",
    "country": "Germany",
    "salary": 183,
    "image": "https://media.guim.co.uk/929479d4241ebd1c99b7f0356b6fff1f907a570f/0_144_5184_3110/500.jpg"
  }, {
    "id": 12,
    "name": "Karim Benzema",
    "present-club": "Sascha Stut",
    "country": "France",
    "salary": 449,
    "image": "https://media.guim.co.uk/c62ea06b76374a174e835de16296b3baa7b7b27a/0_83_5568_3341/500.jpg"
  }, {
    "id": 13,
    "name": "Sergio Ramos",
    "present-club": "Billye Leamy",
    "country": "Spain",
    "salary": 862,
    "image": "https://media.guim.co.uk/fc4905adc2447ab02efa6784c861f49084731e0b/0_61_2704_1622/500.jpg"
  }, {
    "id": 14,
    "name": "Thomas Müller",
    "present-club": "Arlan Cops",
    "country": "Germany",
    "salary": 542,
    "image": "https://idsb.tmgrup.com.tr/ly/uploads/images/2020/04/07/29302.jpg"
  }, {
    "id": 15,
    "name": "Manuel Neuer",
    "present-club": "Shermie Renshaw",
    "country": "Germany",
    "salary": 447,
    "image": "https://media.guim.co.uk/d506a525df7db9be3a2564bc97285de9eb8957ff/268_193_1567_940/500.jpg"
  }, {
    "id": 16,
    "name": "Serge Gnabry",
    "present-club": "Duncan Pennicott",
    "country": "Germany",
    "salary": 607,
    "image": "https://media.guim.co.uk/563b1ce3ceb93b3faf320d28e6689cbb50cd2c1b/0_90_4618_2771/500.jpg"
  }, {
    "id": 17,
    "name": "Thiago Alcântara",
    "present-club": "Dulcie Huge",
    "country": "Spain",
    "salary": 782,
    "image": "https://media.guim.co.uk/50685a4c469f7a60bf02e1e199520efce6531b30/0_37_3783_2270/500.jpg"
  }, {
    "id": 18,
    "name": "Trent Alexander-Arnold",
    "present-club": "Gerick Sargeant",
    "country": "England",
    "salary": 670,
    "image": "https://media.guim.co.uk/5c96fd04b8fea7344fb23443d0fb293c28f9c317/0_79_3312_1987/500.jpg"
  }, {
    "id": 19,
    "name": "Romelu Lukaku",
    "present-club": "Giselbert Baldocci",
    "country": "Belgium",
    "salary": 517,
    "image": "https://media.guim.co.uk/6798fcb66b0118999f985ea546ea5b6c36e31b84/0_209_3000_1800/500.jpg"
  }, {
    "id": 20,
    "name": "Harry Kane",
    "present-club": "Ganny Peealess",
    "country": "England",
    "salary": 156,
    "image": "https://media.guim.co.uk/65682de8ed85e5a6981da3a59887caabb6db670d/242_25_2993_1797/500.jpg"
  }]